validator/__init__.py
validator/_version.py
validator/app.py
validator/default_settings.py
validator/ecosystem_importer.py
validator/read_api.py
validator/training_api.py
validator/utils.py
validator/validate_api.py
validator/write_api.py
validator/ml/__init__.py
validator/ml/stax_string_proc.py
validator/ml/corpora/all_join.txt
validator/ml/corpora/all_plaintext.txt
validator/ml/corpora/bad.txt
validator/ml/corpora/big.txt
validator/ml/corpora/common.txt
validator/ml/corpora/frequency_dictionary_en_82_765.txt
validator/ml/corpora/question_text.txt
validator/ml/corpora/response_validator_spelling_dictionary.txt
validator/ml/corpora/nltk_data/corpora/stopwords.zip
validator/ml/corpora/nltk_data/corpora/words.zip
validator/ml/corpora/nltk_data/corpora/stopwords/README
validator/ml/corpora/nltk_data/corpora/stopwords/arabic
validator/ml/corpora/nltk_data/corpora/stopwords/azerbaijani
validator/ml/corpora/nltk_data/corpora/stopwords/danish
validator/ml/corpora/nltk_data/corpora/stopwords/dutch
validator/ml/corpora/nltk_data/corpora/stopwords/english
validator/ml/corpora/nltk_data/corpora/stopwords/finnish
validator/ml/corpora/nltk_data/corpora/stopwords/french
validator/ml/corpora/nltk_data/corpora/stopwords/german
validator/ml/corpora/nltk_data/corpora/stopwords/greek
validator/ml/corpora/nltk_data/corpora/stopwords/hungarian
validator/ml/corpora/nltk_data/corpora/stopwords/indonesian
validator/ml/corpora/nltk_data/corpora/stopwords/italian
validator/ml/corpora/nltk_data/corpora/stopwords/kazakh
validator/ml/corpora/nltk_data/corpora/stopwords/nepali
validator/ml/corpora/nltk_data/corpora/stopwords/norwegian
validator/ml/corpora/nltk_data/corpora/stopwords/portuguese
validator/ml/corpora/nltk_data/corpora/stopwords/romanian
validator/ml/corpora/nltk_data/corpora/stopwords/russian
validator/ml/corpora/nltk_data/corpora/stopwords/slovene
validator/ml/corpora/nltk_data/corpora/stopwords/spanish
validator/ml/corpora/nltk_data/corpora/stopwords/swedish
response_validator-5.0.1.dist-info/LICENSE.txt
response_validator-5.0.1.dist-info/METADATA
response_validator-5.0.1.dist-info/WHEEL
response_validator-5.0.1.dist-info/top_level.txt
response_validator-5.0.1.dist-info/RECORD
