Metadata-Version: 2.1
Name: response-validator
Version: 5.0.1
Summary: Openstax response validator server
Home-page: https://github.com/openstax/response-validator
Maintainer-email: info@cnx.org
License: AGPL, See also LICENSE.txt
Platform: UNKNOWN
Requires-Dist: flask (>=1.0.2)
Requires-Dist: flask-cors
Requires-Dist: pandas
Requires-Dist: nltk
Requires-Dist: symspellpy
Requires-Dist: sklearn
Requires-Dist: PyYAML
Requires-Dist: requests
Provides-Extra: test
Requires-Dist: pytest ; extra == 'test'
Requires-Dist: coverage ; extra == 'test'
Requires-Dist: vcrpy ; extra == 'test'
